{"results":[{"depth":1,"imageUrl":"https://www.walla.co.il/public/assets/homepage2/new-logo-mobile.svg","sourceUrl":"https://www.walla.co.il"},{"depth":1,"imageUrl":"https://www.walla.co.il/public/assets/icons/icon-weather-mobile.svg","sourceUrl":"https://www.walla.co.il"},{"depth":1,"imageUrl":"https://www.walla.co.il/public/assets/homepage2/icon-mail-no-bg.svg","sourceUrl":"https://www.walla.co.il"},{"depth":1,"imageUrl":"https://www.walla.co.il/public/assets/homepage2/new-logo.svg","sourceUrl":"https://www.walla.co.il"},{"depth":1,"imageUrl":"https://www.walla.co.il/public/assets/icons/allay-icon.svg","sourceUrl":"https://www.walla.co.il"},{"depth":1,"imageUrl":"https://www.walla.co.il/public/assets/icons/yad-2-logo@2x.webp","sourceUrl":"https://www.walla.co.il"},{"depth":1,"imageUrl":"https://www.walla.co.il/public/assets/navigation/tiktok.svg","sourceUrl":"https://www.walla.co.il"},{"depth":1,"imageUrl":"https://www.walla.co.il/public/assets/navigation/insta.svg","sourceUrl":"https://www.walla.co.il"},{"depth":1,"imageUrl":"https://www.walla.co.il/public/assets/navigation/twitter.svg","sourceUrl":"https://www.walla.co.il"},{"depth":1,"imageUrl":"https://www.walla.co.il/public/assets/navigation/facebook.svg","sourceUrl":"https://www.walla.co.il"},{"depth":1,"imageUrl":"https://www.walla.co.il/public/assets/shivuki/invalid-name2.svg","sourceUrl":"https://www.walla.co.il"},{"depth":1,"imageUrl":"https://www.walla.co.il/public/assets/homepage2/radio-stations/103fm.png","sourceUrl":"https://www.walla.co.il"},{"depth":1,"imageUrl":"https://www.walla.co.il/public/assets/homepage2/radio-stations/99fm.png","sourceUrl":"https://www.walla.co.il"},{"depth":1,"imageUrl":"https://www.walla.co.il/public/assets/outbrain/outbrain.png","sourceUrl":"https://www.walla.co.il"},{"depth":1,"imageUrl":"https://www.walla.co.il/public/assets/icons/new-logo-walla-negativ.png","sourceUrl":"https://www.walla.co.il"},{"depth":1,"imageUrl":"https://mc.yandex.ru/watch/91804681","sourceUrl":"https://www.walla.co.il"}]}